pyspotlight-0.7.2.dist-info/DESCRIPTION.rst
pyspotlight-0.7.2.dist-info/METADATA
pyspotlight-0.7.2.dist-info/RECORD
pyspotlight-0.7.2.dist-info/WHEEL
pyspotlight-0.7.2.dist-info/metadata.json
pyspotlight-0.7.2.dist-info/top_level.txt
spotlight/__init__.py
spotlight/tests.py
