Metadata-Version: 1.1
Name: pyspotlight
Version: 0.7.2
Summary: Python interface to the DBpedia Spotlight REST API
Home-page: https://github.com/aolieman/pyspotlight
Author: Alex Olieman
Author-email: alex@olieman.net
License: BSD
Keywords: dbpedia spotlight,semantic annotation,entity linking
Platform: UNKNOWN
Classifier: Intended Audience :: Developers
Classifier: Operating System :: OS Independent
Classifier: Topic :: Software Development :: Libraries
Classifier: Environment :: Web Environment
Classifier: License :: OSI Approved :: BSD License
Classifier: Development Status :: 5 - Production/Stable
Classifier: Programming Language :: Python :: 2.7
Classifier: Programming Language :: Python :: 3.4
Classifier: Programming Language :: Python :: 3.5
